README.rst
setup.cfg
setup.py
src/nexiles/__init__.py
src/nexiles.fabric.tasks.egg-info/PKG-INFO
src/nexiles.fabric.tasks.egg-info/SOURCES.txt
src/nexiles.fabric.tasks.egg-info/dependency_links.txt
src/nexiles.fabric.tasks.egg-info/namespace_packages.txt
src/nexiles.fabric.tasks.egg-info/not-zip-safe
src/nexiles.fabric.tasks.egg-info/requires.txt
src/nexiles.fabric.tasks.egg-info/top_level.txt
src/nexiles/fabric/__init__.py
src/nexiles/fabric/tasks/__init__.py
src/nexiles/fabric/tasks/docs.py
src/nexiles/fabric/tasks/environment.py
src/nexiles/fabric/tasks/gateway.py
src/nexiles/fabric/tasks/log.py
src/nexiles/fabric/tasks/release.py
src/nexiles/fabric/tasks/utils.py
src/nexiles/fabric/tasks/windchill.py