Metadata-Version: 1.1
Name: nexiles.fabric.tasks
Version: 0.1.3
Summary: fabric tasks used at nexiles GmbH
Home-page: https://skynet.nexiles.com/docs/nexiles.fabric.tasks/
Author: Stefan Elethofer
Author-email: stefan.eletzhofer@nexiles.com
License: BSD
Platform: UNKNOWN
Classifier: Intended Audience :: Developers
Classifier: Topic :: Software Development :: Libraries :: Python Modules
